{"client_id": 10, "experiment_id": "LEGOHead_15Client100Benchmark", "ports": {"video": 60030, "result": 60031, "control": 60032}, "run_results": {"init": 1527516562102, "end": 1527516631015, "timestamp_error": 5.059644256269426, "success": true, "ntp_offset": 1706, "frames": [{"frame_id": 39, "sent": 1527516565397, "recv": 1527516565443, "feedback": false}, {"frame_id": 91, "sent": 1527516575648, "recv": 1527516577350, "feedback": false}, {"frame_id": 95, "sent": 1527516578813, "recv": 1527516579811, "feedback": false}, {"frame_id": 150, "sent": 1527516588652, "recv": 1527516589502, "feedback": false}, {"frame_id": 301, "sent": 1527516612986, "recv": 1527516613032, "feedback": false}, {"frame_id": 302, "sent": 1527516613039, "recv": 1527516613082, "feedback": false}, {"frame_id": 303, "sent": 1527516613105, "recv": 1527516613173, "feedback": false}, {"frame_id": 304, "sent": 1527516613174, "recv": 1527516613222, "feedback": false}, {"frame_id": 306, "sent": 1527516613306, "recv": 1527516613364, "feedback": false}, {"frame_id": 307, "sent": 1527516613373, "recv": 1527516613420, "feedback": false}, {"frame_id": 308, "sent": 1527516613440, "recv": 1527516613511, "feedback": false}, {"frame_id": 370, "sent": 1527516622463, "recv": 1527516623031, "feedback": false}]}}